Guia 2 de Practica/G02-E04/Morgan_6_bit.v
module Morgan_6_bit (
    input wire a,
    input wire b,
    input wire c,
    input wire d,
    input wire e,
    input wire f,
    output wire Z,
    output wire G,
    output wire H
);

//Inciso A
assign Z = ~a|(b&c)|~(d&e)|~f;

//Inciso B
assign G= (a&~d)|(a&e)|(a&~f)|(b&~c&~d)|(b&~c&e)|(b&~c&~f);
    
endmodule

Guia 2 de Practica/G02-E04/Morgan_6_bit_tb.v
`default_nettype none
`define DUMPSTR(x) `"x.vcd`"
`timescale 100ns/10ns

module Morgan_6_bit_tb();

parameter DURATION = 10;

reg clk =0;
always #0.5 clk=~clk;

reg test_a, test_b, test_c, test_d, test_e, test_f;
wire test_Z, test_G, test_H;

Morgan_6_bit UUT(
    .a(test_a),
    .b(test_b),
    .c(test_c),
    .d(test_d),
    .e(test_e),
    .f(test_f),
    .Z(test_Z),
    .G(test_G),
    .H(test_H)  
);

integer i;
reg[5:0] i_b;

initial begin
    $dumpfile(`DUMPSTR(`VCD_OUTPUT));
    $dumpvars(0,Morgan_6_bit_tb);

    for (i=0; i<64; i=i+1)
    begin
        $display("Current loop # %0d", i);
        $display("Current loop # %0b", i);

        #1
        i_b=i;
        test_a=i_b[5];
        test_b=i_b[4];
        test_c=i_b[3];
        test_d=i_b[2];
        test_e=i_b[1];
        test_f=i_b[0];
    end

     #(DURATION) $display("End of Simulator");
    $finish;
end

endmodule

Guia 2 de Practica/G02-E04/Morgan_6_bit_tb.vcd
$date
	Wed Apr 05 17:09:45 2023
$end
$version
	Icarus Verilog
$end
$timescale
	1ps
$end
$scope module Morgan_6_bit_tb $end
$var wire 1 ! test_H $end
$var wire 1 " test_Z $end
$var wire 1 # test_G $end
$var reg 1 $ clk $end
$var reg 6 % i_b [5:0] $end
$var reg 1 & test_a $end
$var reg 1 ' test_b $end
$var reg 1 ( test_c $end
$var reg 1 ) test_d $end
$var reg 1 * test_e $end
$var reg 1 + test_f $end
$var integer 32 , i [31:0] $end
$scope module UUT $end
$var wire 1 # G $end
$var wire 1 ! H $end
$var wire 1 " Z $end
$var wire 1 & a $end
$var wire 1 ' b $end
$var wire 1 ( c $end
$var wire 1 ) d $end
$var wire 1 * e $end
$var wire 1 + f $end
$upscope $end
$upscope $end
$enddefinitions $end
#0
$dumpvars
b0 ,
x+
x*
x)
x(
x'
x&
bx %
0$
x#
x"
z!
$end
#50000
1$
#100000
0#
1"
0$
b1 ,
0+
0*
0)
0(
0'
0&
b0 %
#150000
1$
#200000
0$
b10 ,
1+
b1 %
#250000
1$
#300000
0$
b11 ,
0+
1*
b10 %
#350000
1$
#400000
0$
b100 ,
1+
b11 %
#450000
1$
#500000
0$
b101 ,
0+
0*
1)
b100 %
#550000
1$
#600000
0$
b110 ,
1+
b101 %
#650000
1$
#700000
0$
b111 ,
0+
1*
b110 %
#750000
1$
#800000
0$
b1000 ,
1+
b111 %
#850000
1$
#900000
0$
b1001 ,
0+
0*
0)
1(
b1000 %
#950000
1$
#1000000
0$
b1010 ,
1+
b1001 %
#1050000
1$
#1100000
0$
b1011 ,
0+
1*
b1010 %
#1150000
1$
#1200000
0$
b1100 ,
1+
b1011 %
#1250000
1$
#1300000
0$
b1101 ,
0+
0*
1)
b1100 %
#1350000
1$
#1400000
0$
b1110 ,
1+
b1101 %
#1450000
1$
#1500000
0$
b1111 ,
0+
1*
b1110 %
#1550000
1$
#1600000
0$
b10000 ,
1+
b1111 %
#1650000
1$
#1700000
1#
0$
b10001 ,
0+
0*
0)
0(
1'
b10000 %
#1750000
1$
#1800000
0$
b10010 ,
1+
b10001 %
#1850000
1$
#1900000
0$
b10011 ,
0+
1*
b10010 %
#1950000
1$
#2000000
0$
b10100 ,
1+
b10011 %
#2050000
1$
#2100000
0$
b10101 ,
0+
0*
1)
b10100 %
#2150000
1$
#2200000
0#
0$
b10110 ,
1+
b10101 %
#2250000
1$
#2300000
1#
0$
b10111 ,
0+
1*
b10110 %
#2350000
1$
#2400000
0$
b11000 ,
1+
b10111 %
#2450000
1$
#2500000
0#
0$
b11001 ,
0+
0*
0)
1(
b11000 %
#2550000
1$
#2600000
0$
b11010 ,
1+
b11001 %
#2650000
1$
#2700000
0$
b11011 ,
0+
1*
b11010 %
#2750000
1$
#2800000
0$
b11100 ,
1+
b11011 %
#2850000
1$
#2900000
0$
b11101 ,
0+
0*
1)
b11100 %
#2950000
1$
#3000000
0$
b11110 ,
1+
b11101 %
#3050000
1$
#3100000
0$
b11111 ,
0+
1*
b11110 %
#3150000
1$
#3200000
0$
b100000 ,
1+
b11111 %
#3250000
1$
#3300000
1#
0$
b100001 ,
0+
0*
0)
0(
0'
1&
b100000 %
#3350000
1$
#3400000
0$
b100010 ,
1+
b100001 %
#3450000
1$
#3500000
0$
b100011 ,
0+
1*
b100010 %
#3550000
1$
#3600000
0$
b100100 ,
1+
b100011 %
#3650000
1$
#3700000
0$
b100101 ,
0+
0*
1)
b100100 %
#3750000
1$
#3800000
0#
0$
b100110 ,
1+
b100101 %
#3850000
1$
#3900000
1#
0$
b100111 ,
0+
1*
b100110 %
#3950000
1$
#4000000
0"
0$
b101000 ,
1+
b100111 %
#4050000
1$
#4100000
1"
0$
b101001 ,
0+
0*
0)
1(
b101000 %
#4150000
1$
#4200000
0$
b101010 ,
1+
b101001 %
#4250000
1$
#4300000
0$
b101011 ,
0+
1*
b101010 %
#4350000
1$
#4400000
0$
b101100 ,
1+
b101011 %
#4450000
1$
#4500000
0$
b101101 ,
0+
0*
1)
b101100 %
#4550000
1$
#4600000
0#
0$
b101110 ,
1+
b101101 %
#4650000
1$
#4700000
1#
0$
b101111 ,
0+
1*
b101110 %
#4750000
1$
#4800000
0"
0$
b110000 ,
1+
b101111 %
#4850000
1$
#4900000
1"
0$
b110001 ,
0+
0*
0)
0(
1'
b110000 %
#4950000
1$
#5000000
0$
b110010 ,
1+
b110001 %
#5050000
1$
#5100000
0$
b110011 ,
0+
1*
b110010 %
#5150000
1$
#5200000
0$
b110100 ,
1+
b110011 %
#5250000
1$
#5300000
0$
b110101 ,
0+
0*
1)
b110100 %
#5350000
1$
#5400000
0#
0$
b110110 ,
1+
b110101 %
#5450000
1$
#5500000
1#
0$
b110111 ,
0+
1*
b110110 %
#5550000
1$
#5600000
0"
0$
b111000 ,
1+
b110111 %
#5650000
1$
#5700000
1"
0$
b111001 ,
0+
0*
0)
1(
b111000 %
#5750000
1$
#5800000
0$
b111010 ,
1+
b111001 %
#5850000
1$
#5900000
0$
b111011 ,
0+
1*
b111010 %
#5950000
1$
#6000000
0$
b111100 ,
1+
b111011 %
#6050000
1$
#6100000
0$
b111101 ,
0+
0*
1)
b111100 %
#6150000
1$
#6200000
0#
0$
b111110 ,
1+
b111101 %
#6250000
1$
#6300000
1#
0$
b111111 ,
0+
1*
b111110 %
#6350000
1$
#6400000
0$
b1000000 ,
1+
b111111 %
