Guia 2 de Practica/G02-E05/E05_3_bit.v
module E05_3_bit(
    input wire a,
    input wire b,
    input wire c,
    output wire f,
    output wire g,
    output wire h,
    output wire l
);

    assign f = a&b;
    assign g = c;
    assign h = b|(c&(a|b));
    assign l = a&b;
endmodule

Guia 2 de Practica/G02-E05/E05_3_bit_tb.v
`default_nettype none
`define DUMPSTR(x) `"x.vcd`"
`timescale 100ns/10ns

module E05_3_bit_tb();

parameter DURATION = 10;

reg clk =0;
always #0.5 clk=~clk;

reg test_a, test_b, test_c;
wire test_f,test_g,test_h,test_l;

E05_3_bit UUT(
    .a(test_a),
    .b(test_b),
    .c(test_c),
    .f(test_f),
    .g(test_g),
    .h(test_h),
    .l(test_l)
);

integer i;
reg[2:0] i_b;

initial begin
    $dumpfile(`DUMPSTR(`VCD_OUTPUT));
    $dumpvars(0,E05_3_bit_tb);

    for (i=0; i<8; i=i+1)
    begin
        $display("Current loop # %0d", i);
        $display("Current loop # %0b", i);

        #1
        i_b=i;
        test_a=i_b[2];
        test_b=i_b[1];
        test_c=i_b[0];
        
    end

     #(DURATION) $display("End of Simulator");
    $finish;
end
endmodule

Guia 2 de Practica/G02-E05/E05_3_bit_tb.vcd
$date
	Wed Apr 05 17:19:31 2023
$end
$version
	Icarus Verilog
$end
$timescale
	1ps
$end
$scope module E05_3_bit_tb $end
$var wire 1 ! test_l $end
$var wire 1 " test_h $end
$var wire 1 # test_g $end
$var wire 1 $ test_f $end
$var reg 1 % clk $end
$var reg 3 & i_b [2:0] $end
$var reg 1 ' test_a $end
$var reg 1 ( test_b $end
$var reg 1 ) test_c $end
$var integer 32 * i [31:0] $end
$scope module UUT $end
$var wire 1 ' a $end
$var wire 1 ( b $end
$var wire 1 ) c $end
$var wire 1 $ f $end
$var wire 1 # g $end
$var wire 1 " h $end
$var wire 1 ! l $end
$upscope $end
$upscope $end
$enddefinitions $end
#0
$dumpvars
b0 *
x)
x(
x'
bx &
0%
x$
x#
x"
x!
$end
#50000
1%
#100000
0"
0$
0!
0%
b1 *
0#
0)
0(
0'
b0 &
#150000
1%
#200000
0%
b10 *
1#
1)
b1 &
#250000
1%
#300000
1"
0%
b11 *
0#
0)
1(
b10 &
#350000
1%
#400000
0%
b100 *
1#
1)
b11 &
#450000
1%
#500000
0"
0%
b101 *
0#
0)
0(
1'
b100 &
#550000
1%
#600000
1"
0%
b110 *
1#
1)
b101 &
#650000
1%
#700000
1$
1!
0%
b111 *
0#
0)
1(
b110 &
#750000
1%
#800000
0%
b1000 *
1#
1)
b111 &
