Guia 2 de Practica/G02-E07/E07_4_bit.v
module E07_4_bit(
    input wire a,
    input wire b,
    input wire c,
    input wire d,
    output wire y,
    output wire z,
    output wire f2
);

    assign y = (~a&d)|(a&~c&d)|(a&~b&c)|(a&b&c&d); // esta sin simplificar
    assign z = (b&d)|(a&~c&d); // esta sin simplificar
    //assign f2 = (~a&~b&c)|(~a&b&c)|(~b&a); // tomo x,y,z como a,b,c < -- sin simplificar
    assign f2 = (~a&c)|(~b&a); // tomo x,y,z como a,b,c
    
endmodule

Guia 2 de Practica/G02-E07/E07_4_bit_tb.v
`default_nettype none
`define DUMPSTR(x) `"x.vcd`"
`timescale 100ns/10ns

module E07_4_bit_tb();

//-- Tiempo de simulación: 1us (10 * 100ns)
parameter DURATION = 10;

reg clk =0;
always #0.5 clk=~clk;

reg test_a, test_b, test_c,test_d;
wire test_y,test_z,test_f2;

//-- Instanciamos la unidad a probar
E07_4_bit UUT(
    .a(test_a),
    .b(test_b),
    .c(test_c),
    .d(test_d),
    .y(test_y),
    .z(test_z),
    .f2(test_f2)
);

integer i;
reg[3:0] i_b;

initial begin
    $dumpfile(`DUMPSTR(`VCD_OUTPUT));
    $dumpvars(0,E07_4_bit_tb);

    for (i=0; i<16; i=i+1)
    begin
        $display("Bucle actual # %0d", i);
        $display("Bucle actual # %0b", i);

        #1
        i_b=i;
        test_a=i_b[3];
        test_b=i_b[2];
        test_c=i_b[1];
        test_d=i_b[0];
        
    end

     #(DURATION) $display("Fin del simulador");
    $finish;
end
endmodule

Guia 2 de Practica/G02-E07/E07_4_bit_tb.vcd
$date
	Sat Apr 08 12:19:37 2023
$end
$version
	Icarus Verilog
$end
$timescale
	1ps
$end
$scope module E07_4_bit_tb $end
$var wire 1 ! test_z $end
$var wire 1 " test_y $end
$var wire 1 # test_f2 $end
$var reg 1 $ clk $end
$var reg 4 % i_b [3:0] $end
$var reg 1 & test_a $end
$var reg 1 ' test_b $end
$var reg 1 ( test_c $end
$var reg 1 ) test_d $end
$var integer 32 * i [31:0] $end
$scope module UUT $end
$var wire 1 & a $end
$var wire 1 ' b $end
$var wire 1 ( c $end
$var wire 1 ) d $end
$var wire 1 # f2 $end
$var wire 1 " y $end
$var wire 1 ! z $end
$upscope $end
$upscope $end
$enddefinitions $end
#0
$dumpvars
b0 *
x)
x(
x'
x&
bx %
0$
x#
x"
x!
$end
#50000
1$
#100000
0"
0#
0!
0$
b1 *
0)
0(
0'
0&
b0 %
#150000
1$
#200000
1"
0$
b10 *
1)
b1 %
#250000
1$
#300000
0"
1#
0$
b11 *
0)
1(
b10 %
#350000
1$
#400000
1"
0$
b100 *
1)
b11 %
#450000
1$
#500000
0"
0#
0$
b101 *
0)
0(
1'
b100 %
#550000
1$
#600000
1"
1!
0$
b110 *
1)
b101 %
#650000
1$
#700000
0"
1#
0!
0$
b111 *
0)
1(
b110 %
#750000
1$
#800000
1"
1!
0$
b1000 *
1)
b111 %
#850000
1$
#900000
0"
0!
0$
b1001 *
0)
0(
0'
1&
b1000 %
#950000
1$
#1000000
1"
1!
0$
b1010 *
1)
b1001 %
#1050000
1$
#1100000
0!
0$
b1011 *
0)
1(
b1010 %
#1150000
1$
#1200000
0$
b1100 *
1)
b1011 %
#1250000
1$
#1300000
0"
0#
0$
b1101 *
0)
0(
1'
b1100 %
#1350000
1$
#1400000
1"
1!
0$
b1110 *
1)
b1101 %
#1450000
1$
#1500000
0"
0!
0$
b1111 *
0)
1(
b1110 %
#1550000
1$
#1600000
1"
1!
0$
b10000 *
1)
b1111 %
